{"distinct_id": "lqeKhAWUDaI", "event_name": "RC Expiration", "insert_id": "c2ba19b2-e447-4097-8112-6e469f01ac49", "properties": {"$insert_id": "c2ba19b2-e447-4097-8112-6e469f01ac49", "$mp_api_endpoint": "api.mixpanel.com", "$mp_api_timestamp_ms": 1753760203428, "aliases": ["lqeKhAWUDaI"], "app_id": "app5d7fea992a", "currency": "USD", "entitlement_id": null, "entitlement_ids": ["CwX3l0tJjXE"], "environment": "PRODUCTION", "expiration_at": "2025-07-29T03:36:36", "expiration_reason": "UNSUBSCRIBE", "mp_processing_time_ms": 1753760203454, "offer_code": null, "original_app_user_id": "lqeKhAWUDaI", "original_transaction_id": "si_SixxpycXOdc0KZ", "period_type": "NORMAL", "presented_offering_id": null, "product_id": "prod_R7oYuL3bSUecnr", "purchased_at": "2025-07-29T02:34:16", "revenue": 0, "store": "STRIPE", "subscriber_attributes": {}, "transaction_id": "si_SixxpycXOdc0KZ"}, "time": 1753760196}
{"distinct_id": "lqeKhAWUDaI", "event_name": "RC Cancellation", "insert_id": "760c6334-f219-444b-9265-845ea08c0eec", "properties": {"$insert_id": "760c6334-f219-444b-9265-845ea08c0eec", "$mp_api_endpoint": "api.mixpanel.com", "$mp_api_timestamp_ms": 1753760203338, "aliases": ["lqeKhAWUDaI"], "app_id": "app5d7fea992a", "cancel_reason": "UNSUBSCRIBE", "currency": "USD", "entitlement_id": null, "entitlement_ids": ["CwX3l0tJjXE"], "environment": "PRODUCTION", "expiration_at": "2025-07-29T03:36:36", "mp_processing_time_ms": 1753760203410, "offer_code": null, "original_app_user_id": "lqeKhAWUDaI", "original_transaction_id": "si_SixxpycXOdc0KZ", "period_type": "NORMAL", "presented_offering_id": null, "product_id": "prod_R7oYuL3bSUecnr", "purchased_at": "2025-07-29T02:34:16", "revenue": 0, "store": "STRIPE", "subscriber_attributes": {}, "transaction_id": "si_SixxpycXOdc0KZ"}, "time": 1753760203}
{"distinct_id": "wxKXcTGqgK2", "event_name": "RC Cancellation", "insert_id": "abcb97c5-0700-4834-820b-aca8e3d2a0e8", "properties": {"$distinct_id_before_identity": "$device:48D9FF47-E774-4CB9-A1A1-66C4534C3C46", "$insert_id": "abcb97c5-0700-4834-820b-aca8e3d2a0e8", "$mp_api_endpoint": "api.mixpanel.com", "$mp_api_timestamp_ms": 1753758560927, "aliases": ["$RCAnonymousID:293e8448584e4859bfbd828f25844275", "wxKXcTGqgK2"], "app_id": "app5d7fea992a", "cancel_reason": "UNSUBSCRIBE", "currency": "USD", "entitlement_id": null, "entitlement_ids": ["CwX3l0tJjXE"], "environment": "PRODUCTION", "expiration_at": "2026-07-28T23:07:11", "mp_processing_time_ms": 1753758561762, "offer_code": null, "original_app_user_id": "wxKXcTGqgK2", "original_transaction_id": "si_Siuc9olEv8icpW", "period_type": "NORMAL", "presented_offering_id": null, "product_id": "prod_R7oYuL3bSUecnr", "purchased_at": "2025-07-28T23:07:11", "revenue": 0, "store": "STRIPE", "subscriber_attributes": {"$attConsentStatus": "notDetermined", "$branchId": "$device:48D9FF47-E774-4CB9-A1A1-66C4534C3C46", "$deviceVersion": "iPhone14,5-iOS-Version 17.1.2 (Build 21B101)", "$firebaseAppInstanceId": "FA501916941B4ADCA2F9C66136CA3FA0", "$idfa": "00000000-0000-0000-0000-000000000000", "$idfv": "D3EE4623-1A9C-452C-A07D-94839E64F5E6", "$ip": "174.199.33.101", "$mixpanelDistinctId": "$device:48D9FF47-E774-4CB9-A1A1-66C4534C3C46"}, "transaction_id": "si_Siuc9olEv8icpW"}, "time": 1753758560}
{"distinct_id": "$device:9D48B0E6-7AE1-4BC2-B098-032A4CC8333C", "event_name": "RC Trial cancelled", "insert_id": "ec063cf5-ebcf-4cff-8469-0d9479a5050a", "properties": {"$insert_id": "ec063cf5-ebcf-4cff-8469-0d9479a5050a", "$mp_api_endpoint": "api.mixpanel.com", "$mp_api_timestamp_ms": 1753761496282, "aliases": ["$RCAnonymousID:c9c77f43e0de466a893e97e39593e8b5"], "app_id": "app5fe9d54dee", "cancel_reason": "BILLING_ERROR", "currency": "INR", "entitlement_id": null, "entitlement_ids": ["CwX3l0tJjXE"], "environment": "PRODUCTION", "expiration_at": "2025-08-01T03:57:29", "mp_processing_time_ms": 1753761496306, "offer_code": null, "original_app_user_id": "$RCAnonymousID:c9c77f43e0de466a893e97e39593e8b5", "original_transaction_id": "550002381430386", "period_type": "TRIAL", "presented_offering_id": null, "product_id": "gluten.free.eats.winback.yearly", "purchased_at": "2025-07-22T03:57:29", "revenue": 0, "store": "APP_STORE", "subscriber_attributes": {"$attConsentStatus": "notDetermined", "$branchId": "$device:9D48B0E6-7AE1-4BC2-B098-032A4CC8333C", "$deviceVersion": "iPhone14,5-iOS-Version 18.5 (Build 22F76)", "$firebaseAppInstanceId": "4863CB28DA6247FF80B5CF16F327EA00", "$idfa": "00000000-0000-0000-0000-000000000000", "$idfv": "61DE220F-9E88-4F99-89FA-751126E06DF4", "$ip": "174.119.253.15", "$mixpanelDistinctId": "$device:9D48B0E6-7AE1-4BC2-B098-032A4CC8333C"}, "transaction_id": "550002381430386"}, "time": 1753761496}
{"distinct_id": "$device:6EAD87A1-7C87-448F-85C7-4F04B64D8452", "event_name": "RC Trial cancelled", "insert_id": "0183592f-4e2f-4174-ad1a-7ff86f8431e5", "properties": {"$insert_id": "0183592f-4e2f-4174-ad1a-7ff86f8431e5", "$mp_api_endpoint": "api.mixpanel.com", "$mp_api_timestamp_ms": 1753758387126, "aliases": ["A7TEdiTwK7B", "$RCAnonymousID:4feee7a837884b35bd24abac191a8705"], "app_id": "app5fe9d54dee", "cancel_reason": "UNSUBSCRIBE", "currency": "SEK", "entitlement_id": null, "entitlement_ids": ["CwX3l0tJjXE"], "environment": "PRODUCTION", "expiration_at": "2025-08-04T22:30:01", "mp_processing_time_ms": 1753758387223, "offer_code": null, "original_app_user_id": "$RCAnonymousID:4feee7a837884b35bd24abac191a8705", "original_transaction_id": "490002319044271", "period_type": "TRIAL", "presented_offering_id": "gluten.free.eats.3", "product_id": "gluten.free.eats.3.yearly", "purchased_at": "2025-07-28T22:30:01", "revenue": 0, "store": "APP_STORE", "subscriber_attributes": {"$attConsentStatus": "notDetermined", "$branchId": "$device:6EAD87A1-7C87-448F-85C7-4F04B64D8452", "$deviceVersion": "iPhone13,1-iOS-Version 18.5 (Build 22F76)", "$firebaseAppInstanceId": "2E63534BD4684A8A8CB8759F593F4B6D", "$idfa": "00000000-0000-0000-0000-000000000000", "$idfv": "F7D903B0-E238-4CFA-BE6D-574519E79254", "$ip": "87.227.117.70", "$mixpanelDistinctId": "$device:6EAD87A1-7C87-448F-85C7-4F04B64D8452"}, "transaction_id": "490002319044271"}, "time": 1753758386}
{"distinct_id": "$device:b8997d9d-dd70-4f0f-af29-73f16a7dddcb", "event_name": "RC Renewal", "insert_id": "9105bbdb-7ec5-4050-b609-768dbc8221cc", "properties": {"$distinct_id_before_identity": "dkj-YVVqG7W", "$insert_id": "9105bbdb-7ec5-4050-b609-768dbc8221cc", "$mp_api_endpoint": "api.mixpanel.com", "$mp_api_timestamp_ms": 1753762487850, "aliases": ["dkj-YVVqG7W"], "app_id": "app3a26e6fb19", "currency": "USD", "entitlement_id": null, "entitlement_ids": ["CwX3l0tJjXE"], "environment": "PRODUCTION", "expiration_at": "2025-08-29T03:30:11", "mp_processing_time_ms": 1753762487889, "offer_code": null, "original_app_user_id": "dkj-YVVqG7W", "original_transaction_id": "GPA.3321-4632-9658-66305", "period_type": "NORMAL", "presented_offering_id": "gluten.free.eats.3", "product_id": "gluten_free_subscription:gluten-free-map-monthly-3", "purchased_at": "2025-07-29T03:30:11", "revenue": 13.99, "store": "PLAY_STORE", "subscriber_attributes": {"$branchId": "dkj-YVVqG7W", "$deviceVersion": "motorola edge plus 5G UW (2022)-android-34", "$firebaseAppInstanceId": "6fc27dfee2d3461e41331de58e08e4e2", "$gpsAdId": "426e7d39-a306-4329-bf70-cdd29b289852", "$ip": "174.26.224.32", "$mixpanelDistinctId": "dkj-YVVqG7W"}, "transaction_id": "GPA.3321-4632-9658-66305..1"}, "time": 1753759811}
{"distinct_id": "$device:F7DEFE5A-9B98-4BEA-B1C6-3BD571105299", "event_name": "RC Trial converted", "insert_id": "52500715-1847-4489-9f6c-254962dfb1b5", "properties": {"$insert_id": "52500715-1847-4489-9f6c-254962dfb1b5", "$mp_api_endpoint": "api.mixpanel.com", "$mp_api_timestamp_ms": 1753761326503, "aliases": ["$RCAnonymousID:7f09404c48d74045871049a1fa7cdf2e", "mZU4VlIEk-0"], "app_id": "app5fe9d54dee", "currency": "GBP", "entitlement_id": null, "entitlement_ids": ["CwX3l0tJjXE"], "environment": "PRODUCTION", "expiration_at": "2026-07-29T11:54:24", "mp_processing_time_ms": 1753761326544, "offer_code": null, "original_app_user_id": "$RCAnonymousID:7f09404c48d74045871049a1fa7cdf2e", "original_transaction_id": "480002585378926", "period_type": "NORMAL", "presented_offering_id": "gluten.free.eats.3", "product_id": "gluten.free.eats.3.yearly", "purchased_at": "2025-07-29T11:54:24", "revenue": 66.747, "store": "APP_STORE", "subscriber_attributes": {"$attConsentStatus": "denied", "$branchId": "$device:F7DEFE5A-9B98-4BEA-B1C6-3BD571105299", "$deviceVersion": "iPhone17,2-iOS-Version 18.5 (Build 22F76)", "$firebaseAppInstanceId": "284664DF285B4959B8F9B9E171B05C6C", "$idfa": "00000000-0000-0000-0000-000000000000", "$idfv": "40667109-6142-4942-9164-66DAF54F1FDC", "$ip": "82.132.237.227", "$mixpanelDistinctId": "$device:F7DEFE5A-9B98-4BEA-B1C6-3BD571105299"}, "transaction_id": "480002594933593"}, "time": 1753761326}
{"distinct_id": "198302272ed1f6f-011fac59a38d71-2e43092d-61d78-198302272ee2ea3", "event_name": "RC Expiration", "insert_id": "2a4fb014-f79a-438e-9da6-3e434d47a0b1", "properties": {"$distinct_id_before_identity": "$device:945631F1-2423-493F-8081-7EC3EC93F519", "$insert_id": "2a4fb014-f79a-438e-9da6-3e434d47a0b1", "$mp_api_endpoint": "api.mixpanel.com", "$mp_api_timestamp_ms": 1753759271056, "aliases": ["$RCAnonymousID:78db677597fd4c8799b261726d122a76", "UaNDgdORZcB"], "app_id": "app5fe9d54dee", "currency": "INR", "entitlement_id": null, "entitlement_ids": ["CwX3l0tJjXE"], "environment": "PRODUCTION", "expiration_at": "2025-07-29T03:20:30", "expiration_reason": "UNSUBSCRIBE", "mp_processing_time_ms": 1753759271114, "offer_code": null, "original_app_user_id": "$RCAnonymousID:78db677597fd4c8799b261726d122a76", "original_transaction_id": "600002098322888", "period_type": "TRIAL", "presented_offering_id": "gluten.free.eats.3", "product_id": "gluten.free.eats.3.yearly", "purchased_at": "2025-07-22T03:20:30", "revenue": 0, "store": "APP_STORE", "subscriber_attributes": {"$attConsentStatus": "notDetermined", "$branchId": "$device:945631F1-2423-493F-8081-7EC3EC93F519", "$deviceVersion": "iPhone15,5-iOS-Version 18.5 (Build 22F76)", "$firebaseAppInstanceId": "FFE84727BBB34737B1E4B3C2D2EEE8BE", "$idfa": "00000000-0000-0000-0000-000000000000", "$idfv": "6ABFEC2A-83A2-4DFC-82BB-0D7498A94806", "$ip": "223.189.121.116", "$mixpanelDistinctId": "$device:945631F1-2423-493F-8081-7EC3EC93F519"}, "transaction_id": "600002098322888"}, "time": 1753759230}
{"distinct_id": "$device:C2ADA8EA-BD90-4E67-AC46-BD1404D10248", "event_name": "RC Trial started", "insert_id": "3a84ca0f-15b9-4c32-8523-fe9c9a685c22", "properties": {"$insert_id": "3a84ca0f-15b9-4c32-8523-fe9c9a685c22", "$mp_api_endpoint": "api.mixpanel.com", "$mp_api_timestamp_ms": 1753760872529, "aliases": ["$RCAnonymousID:b864272f34c44c9b8e3bf3956c1f12b0"], "app_id": "app5fe9d54dee", "currency": "AUD", "entitlement_id": null, "entitlement_ids": ["CwX3l0tJjXE"], "environment": "PRODUCTION", "expiration_at": "2025-08-05T03:47:42", "mp_processing_time_ms": 1753760878879, "offer_code": null, "original_app_user_id": "$RCAnonymousID:b864272f34c44c9b8e3bf3956c1f12b0", "original_transaction_id": "210002357486788", "period_type": "TRIAL", "presented_offering_id": "gluten.free.eats.3", "product_id": "gluten.free.eats.3.yearly", "purchased_at": "2025-07-29T03:47:42", "revenue": 0, "store": "APP_STORE", "subscriber_attributes": {"$attConsentStatus": "denied", "$branchId": "$device:C2ADA8EA-BD90-4E67-AC46-BD1404D10248", "$deviceVersion": "iPhone13,4-iOS-Version 18.5 (Build 22F76)", "$firebaseAppInstanceId": "04BDA28CB8CA4988B31C432792401DD6", "$idfa": "00000000-0000-0000-0000-000000000000", "$idfv": "A74E04BA-7175-49E1-9B37-14200563E543", "$ip": "115.85.71.234", "$mixpanelDistinctId": "$device:C2ADA8EA-BD90-4E67-AC46-BD1404D10248"}, "transaction_id": "210002357486788"}, "time": 1753760862}
{"distinct_id": "0fJT1Oh4VIk", "event_name": "RC Expiration", "insert_id": "aa8ff94a-bddc-4b98-8cae-5a21eecefd06", "properties": {"$distinct_id_before_identity": "$device:A0206C92-905C-4ADF-8F26-BF0AB640A6DB", "$insert_id": "aa8ff94a-bddc-4b98-8cae-5a21eecefd06", "$mp_api_endpoint": "api.mixpanel.com", "$mp_api_timestamp_ms": 1753760270493, "aliases": ["$RCAnonymousID:0dc01e5a0ec647b99d82cc589f155939", "0fJT1Oh4VIk"], "app_id": "app5d7fea992a", "currency": "USD", "entitlement_id": null, "entitlement_ids": ["CwX3l0tJjXE"], "environment": "PRODUCTION", "expiration_at": "2025-07-29T03:37:43", "expiration_reason": "UNSUBSCRIBE", "mp_processing_time_ms": 1753760270563, "offer_code": null, "original_app_user_id": "$RCAnonymousID:0dc01e5a0ec647b99d82cc589f155939", "original_transaction_id": "si_SixzvO8TbUX54J", "period_type": "NORMAL", "presented_offering_id": null, "product_id": "prod_R7oYuL3bSUecnr", "purchased_at": "2025-07-29T02:35:56", "revenue": 0, "store": "STRIPE", "subscriber_attributes": {"$attConsentStatus": "notDetermined", "$branchId": "$device:A0206C92-905C-4ADF-8F26-BF0AB640A6DB", "$deviceVersion": "iPhone14,2-iOS-Version 18.5 (Build 22F76)", "$firebaseAppInstanceId": "CB28DCCD1DC44419874C9199D08E8180", "$idfa": "00000000-0000-0000-0000-000000000000", "$idfv": "B4E9B4CA-0F5B-4DFD-8686-DE76A43F1000", "$ip": "119.18.1.179", "$mixpanelDistinctId": "$device:A0206C92-905C-4ADF-8F26-BF0AB640A6DB"}, "transaction_id": "si_SixzvO8TbUX54J"}, "time": 1753760263}
{"distinct_id": "0fJT1Oh4VIk", "event_name": "RC Cancellation", "insert_id": "6708520c-531a-4bfb-a6b5-004be91d57f7", "properties": {"$distinct_id_before_identity": "$device:A0206C92-905C-4ADF-8F26-BF0AB640A6DB", "$insert_id": "6708520c-531a-4bfb-a6b5-004be91d57f7", "$mp_api_endpoint": "api.mixpanel.com", "$mp_api_timestamp_ms": 1753760270499, "aliases": ["$RCAnonymousID:0dc01e5a0ec647b99d82cc589f155939", "0fJT1Oh4VIk"], "app_id": "app5d7fea992a", "cancel_reason": "UNSUBSCRIBE", "currency": "USD", "entitlement_id": null, "entitlement_ids": ["CwX3l0tJjXE"], "environment": "PRODUCTION", "expiration_at": "2025-07-29T03:37:43", "mp_processing_time_ms": 1753760270909, "offer_code": null, "original_app_user_id": "$RCAnonymousID:0dc01e5a0ec647b99d82cc589f155939", "original_transaction_id": "si_SixzvO8TbUX54J", "period_type": "NORMAL", "presented_offering_id": null, "product_id": "prod_R7oYuL3bSUecnr", "purchased_at": "2025-07-29T02:35:56", "revenue": 0, "store": "STRIPE", "subscriber_attributes": {"$attConsentStatus": "notDetermined", "$branchId": "$device:A0206C92-905C-4ADF-8F26-BF0AB640A6DB", "$deviceVersion": "iPhone14,2-iOS-Version 18.5 (Build 22F76)", "$firebaseAppInstanceId": "CB28DCCD1DC44419874C9199D08E8180", "$idfa": "00000000-0000-0000-0000-000000000000", "$idfv": "B4E9B4CA-0F5B-4DFD-8686-DE76A43F1000", "$ip": "119.18.1.179", "$mixpanelDistinctId": "$device:A0206C92-905C-4ADF-8F26-BF0AB640A6DB"}, "transaction_id": "si_SixzvO8TbUX54J"}, "time": 1753760270}
{"distinct_id": "$device:3C6AB66D-ACF7-40A7-930D-C49FB26B1BA6", "event_name": "RC Cancellation", "insert_id": "a4a1d658-076d-4ea5-977d-f6db69cd5058", "properties": {"$insert_id": "a4a1d658-076d-4ea5-977d-f6db69cd5058", "$mp_api_endpoint": "api.mixpanel.com", "$mp_api_timestamp_ms": 1753758424605, "aliases": ["$RCAnonymousID:45c1a159ddaf421993bbb4f3f1e24de9"], "app_id": "app5fe9d54dee", "cancel_reason": "UNSUBSCRIBE", "currency": "USD", "entitlement_id": null, "entitlement_ids": ["CwX3l0tJjXE"], "environment": "PRODUCTION", "expiration_at": "2025-09-13T23:17:32", "mp_processing_time_ms": 1753758424626, "offer_code": null, "original_app_user_id": "$RCAnonymousID:45c1a159ddaf421993bbb4f3f1e24de9", "original_transaction_id": "30002183983714", "period_type": "NORMAL", "presented_offering_id": "CwX3l0tJjXE_2", "product_id": "glutenfree_map.CwX3l0tJjXE.12m2", "purchased_at": "2024-09-13T23:17:32", "revenue": 0, "store": "APP_STORE", "subscriber_attributes": {"$attConsentStatus": "notDetermined", "$branchId": "$device:3C6AB66D-ACF7-40A7-930D-C49FB26B1BA6", "$firebaseAppInstanceId": "48BD24BDE60A4466A3D5CA7D85CE3B78", "$idfa": "00000000-0000-0000-0000-000000000000", "$idfv": "2CAD001D-BBCB-442F-A1AE-C33AC77C8788", "$ip": "64.121.211.153", "$mixpanelDistinctId": "$device:3C6AB66D-ACF7-40A7-930D-C49FB26B1BA6"}, "transaction_id": "30002193893157"}, "time": 1753758424}
{"distinct_id": "$device:d6b3fae2-a461-4901-8433-8cb70b795834", "event_name": "RC Cancellation", "insert_id": "94137405-9e1d-4dad-9eae-d9eb8e60d103", "properties": {"$distinct_id_before_identity": "z3pHT6RxKag", "$insert_id": "94137405-9e1d-4dad-9eae-d9eb8e60d103", "$mp_api_endpoint": "api.mixpanel.com", "$mp_api_timestamp_ms": 1753760418752, "aliases": ["z3pHT6RxKag"], "app_id": "app3a26e6fb19", "cancel_reason": "CUSTOMER_SUPPORT", "currency": "CAD", "entitlement_id": null, "entitlement_ids": ["CwX3l0tJjXE"], "environment": "PRODUCTION", "expiration_at": "2025-07-28T21:01:06", "mp_processing_time_ms": 1753760429544, "offer_code": null, "original_app_user_id": "z3pHT6RxKag", "original_transaction_id": "GPA.3314-2936-9394-81591", "period_type": "NORMAL", "presented_offering_id": "gluten.free.eats.3", "product_id": "gluten_free_subscription:gluten-free-map-yearly-3", "purchased_at": "2025-07-28T20:44:06", "revenue": 0, "store": "PLAY_STORE", "subscriber_attributes": {"$branchId": "z3pHT6RxKag", "$deviceVersion": "Pixel 8-android-35", "$firebaseAppInstanceId": "405e275b25d8fa2617522ae9fda1b095", "$gpsAdId": "69bb6f62-9898-4149-acf0-34a19b7ccadf", "$ip": "66.130.119.100", "$mixpanelDistinctId": "z3pHT6RxKag"}, "transaction_id": "GPA.3314-2936-9394-81591..0"}, "time": 1753760418}
{"distinct_id": "$device:1B9D0516-B57C-4E7B-97F2-DF65D8BD6754", "event_name": "RC Trial started", "insert_id": "7ab44a35-4cc2-4273-996c-1cfe7d71bffc", "properties": {"$insert_id": "7ab44a35-4cc2-4273-996c-1cfe7d71bffc", "$mp_api_endpoint": "api.mixpanel.com", "$mp_api_timestamp_ms": 1753761333373, "aliases": ["$RCAnonymousID:8ab91dc179944ea784948027650d2ec6"], "app_id": "app5fe9d54dee", "currency": "AUD", "entitlement_id": null, "entitlement_ids": ["CwX3l0tJjXE"], "environment": "PRODUCTION", "expiration_at": "2025-08-05T03:55:24", "mp_processing_time_ms": 1753761333427, "offer_code": null, "original_app_user_id": "$RCAnonymousID:8ab91dc179944ea784948027650d2ec6", "original_transaction_id": "390001849966271", "period_type": "TRIAL", "presented_offering_id": "gluten.free.eats.3", "product_id": "gluten.free.eats.3.yearly", "purchased_at": "2025-07-29T03:55:24", "revenue": 0, "store": "APP_STORE", "subscriber_attributes": {"$attConsentStatus": "notDetermined", "$branchId": "$device:1B9D0516-B57C-4E7B-97F2-DF65D8BD6754", "$deviceVersion": "iPhone17,2-iOS-Version 18.5 (Build 22F76)", "$firebaseAppInstanceId": "356DE0E121294652AC3A86BA544B0D1C", "$idfa": "00000000-0000-0000-0000-000000000000", "$idfv": "38FD2880-10B7-44F9-A0B9-A7ADF063EB87", "$ip": "173.198.69.239", "$mixpanelDistinctId": "$device:1B9D0516-B57C-4E7B-97F2-DF65D8BD6754"}, "transaction_id": "390001849966271"}, "time": 1753761324}
{"distinct_id": "$device:305990BC-7C57-4FEF-AD12-7429ECFC539E", "event_name": "RC Cancellation", "insert_id": "68826bcc-65c4-4cc5-9cd1-c6699f822c47", "properties": {"$insert_id": "68826bcc-65c4-4cc5-9cd1-c6699f822c47", "$mp_api_endpoint": "api.mixpanel.com", "$mp_api_timestamp_ms": 1753760503673, "aliases": ["$RCAnonymousID:f7f0a8a9583544b8b8289bbc229953b3", "ygEMqFRtB28"], "app_id": "app5fe9d54dee", "cancel_reason": "UNSUBSCRIBE", "currency": "AUD", "entitlement_id": null, "entitlement_ids": ["CwX3l0tJjXE"], "environment": "PRODUCTION", "expiration_at": "2025-08-19T03:51:59", "mp_processing_time_ms": 1753760504282, "offer_code": null, "original_app_user_id": "$RCAnonymousID:f7f0a8a9583544b8b8289bbc229953b3", "original_transaction_id": "370002143082854", "period_type": "NORMAL", "presented_offering_id": null, "product_id": "gluten.free.eats.3.monthly", "purchased_at": "2025-07-19T03:51:59", "revenue": 0, "store": "APP_STORE", "subscriber_attributes": {"$attConsentStatus": "notDetermined", "$branchId": "$device:305990BC-7C57-4FEF-AD12-7429ECFC539E", "$deviceVersion": "iPhone17,1-iOS-Version 18.5 (Build 22F76)", "$firebaseAppInstanceId": "A845F04BCAC343F79E5AF6F8DD3DC374", "$idfa": "00000000-0000-0000-0000-000000000000", "$idfv": "FFAE1EAB-332E-4552-A991-D1684D09442E", "$ip": "120.21.3.75", "$mixpanelDistinctId": "$device:305990BC-7C57-4FEF-AD12-7429ECFC539E"}, "transaction_id": "370002151622652"}, "time": 1753760503}
{"distinct_id": "$device:F67C8D80-9039-4442-B7E4-06A3B83C92E6", "event_name": "RC Renewal", "insert_id": "908931bf-6640-419d-9982-2a815dcb3fd7", "properties": {"$insert_id": "908931bf-6640-419d-9982-2a815dcb3fd7", "$mp_api_endpoint": "api.mixpanel.com", "$mp_api_timestamp_ms": 1753760662513, "aliases": ["Si7Hou8ybXJ", "$RCAnonymousID:bd0255e177394e9da3cc57a8094c3f22"], "app_id": "app5fe9d54dee", "currency": "USD", "entitlement_id": null, "entitlement_ids": ["CwX3l0tJjXE"], "environment": "PRODUCTION", "expiration_at": "2025-08-29T11:43:52", "mp_processing_time_ms": 1753760662551, "offer_code": null, "original_app_user_id": "$RCAnonymousID:bd0255e177394e9da3cc57a8094c3f22", "original_transaction_id": "360002436711618", "period_type": "NORMAL", "presented_offering_id": "gluten.free.eats.3", "product_id": "gluten.free.eats.3.monthly", "purchased_at": "2025-07-29T11:43:52", "revenue": 13.99, "store": "APP_STORE", "subscriber_attributes": {"$attConsentStatus": "denied", "$branchId": "$device:F67C8D80-9039-4442-B7E4-06A3B83C92E6", "$deviceVersion": "iPhone16,2-iOS-Version 18.5 (Build 22F76)", "$firebaseAppInstanceId": "147692D8CE2341C1A5823FC022368FC1", "$idfa": "00000000-0000-0000-0000-000000000000", "$idfv": "290D339A-3DB7-4496-BA22-AFA714AD3FE5", "$ip": "73.86.202.76", "$mixpanelDistinctId": "$device:F67C8D80-9039-4442-B7E4-06A3B83C92E6"}, "transaction_id": "360002491085969"}, "time": 1753760662}
{"distinct_id": "$device:77d3445d-7cd5-47f6-91f1-4d6cc38b4cc2", "event_name": "RC Expiration", "insert_id": "ac9a64c5-b994-4378-a1e0-0af69d27c301", "properties": {"$distinct_id_before_identity": "ANTxHAN6R7H", "$insert_id": "ac9a64c5-b994-4378-a1e0-0af69d27c301", "$mp_api_endpoint": "api.mixpanel.com", "$mp_api_timestamp_ms": 1753762041350, "aliases": ["ANTxHAN6R7H"], "app_id": "app3a26e6fb19", "currency": "CAD", "entitlement_id": null, "entitlement_ids": ["CwX3l0tJjXE"], "environment": "PRODUCTION", "expiration_at": "2025-07-29T03:19:30", "expiration_reason": "UNSUBSCRIBE", "mp_processing_time_ms": 1753762041520, "offer_code": "gluten-free-map-winback-yearly-free-trial", "original_app_user_id": "ANTxHAN6R7H", "original_transaction_id": "GPA.3338-1893-4643-43197", "period_type": "TRIAL", "presented_offering_id": "gluten.free.eats.winback", "product_id": "gluten_free_subscription:gluten-free-map-winback-yearly", "purchased_at": "2025-07-22T03:19:33", "revenue": 0, "store": "PLAY_STORE", "subscriber_attributes": {}, "transaction_id": "GPA.3338-1893-4643-43197"}, "time": 1753759170}
{"distinct_id": "$device:C5FC71D1-7D7A-4F36-91BA-0829A85165BE", "event_name": "RC Expiration", "insert_id": "16d0cd79-229c-4eb6-a93f-92724e8741fd", "properties": {"$insert_id": "16d0cd79-229c-4eb6-a93f-92724e8741fd", "$mp_api_endpoint": "api.mixpanel.com", "$mp_api_timestamp_ms": 1753758729053, "aliases": ["$RCAnonymousID:a49b88f76170421d97d10b9710120717", "e8KRowyfuyH"], "app_id": "app5fe9d54dee", "currency": "USD", "entitlement_id": null, "entitlement_ids": ["CwX3l0tJjXE"], "environment": "PRODUCTION", "expiration_at": "2025-07-29T03:11:16", "expiration_reason": "UNSUBSCRIBE", "mp_processing_time_ms": 1753758729102, "offer_code": null, "original_app_user_id": "$RCAnonymousID:a49b88f76170421d97d10b9710120717", "original_transaction_id": "210002347480867", "period_type": "TRIAL", "presented_offering_id": "gluten.free.eats.3", "product_id": "gluten.free.eats.3.monthly", "purchased_at": "2025-07-22T03:11:16", "revenue": 0, "store": "APP_STORE", "subscriber_attributes": {"$attConsentStatus": "notDetermined", "$branchId": "$device:C5FC71D1-7D7A-4F36-91BA-0829A85165BE", "$deviceVersion": "iPhone14,3-iOS-Version 18.5 (Build 22F76)", "$firebaseAppInstanceId": "3045F243B928497A814A028C50511B83", "$idfa": "00000000-0000-0000-0000-000000000000", "$idfv": "5FF4F610-D302-4755-B629-9F26FCC24F76", "$ip": "152.117.105.21", "$mixpanelDistinctId": "$device:C5FC71D1-7D7A-4F36-91BA-0829A85165BE"}, "transaction_id": "210002347480867"}, "time": 1753758676}
{"distinct_id": "$device:51B72A3B-5502-4A71-BEAA-7C6571E1A5D0", "event_name": "RC Trial cancelled", "insert_id": "d431f8be-fdf7-48ca-a62f-9277286be1cf", "properties": {"$insert_id": "d431f8be-fdf7-48ca-a62f-9277286be1cf", "$mp_api_endpoint": "api.mixpanel.com", "$mp_api_timestamp_ms": 1753758248159, "aliases": ["$RCAnonymousID:61a23a832b0a44089d285de3cd580b75", "_LnhGYh8rCh"], "app_id": "app5fe9d54dee", "cancel_reason": "UNSUBSCRIBE", "currency": "CAD", "entitlement_id": null, "entitlement_ids": ["CwX3l0tJjXE"], "environment": "PRODUCTION", "expiration_at": "2025-08-05T02:58:37", "mp_processing_time_ms": 1753758255576, "offer_code": null, "original_app_user_id": "$RCAnonymousID:61a23a832b0a44089d285de3cd580b75", "original_transaction_id": "170002896205359", "period_type": "TRIAL", "presented_offering_id": "gluten.free.eats.3", "product_id": "gluten.free.eats.3.yearly", "purchased_at": "2025-07-29T02:58:37", "revenue": 0, "store": "APP_STORE", "subscriber_attributes": {"$attConsentStatus": "denied", "$branchId": "$device:51B72A3B-5502-4A71-BEAA-7C6571E1A5D0", "$deviceVersion": "iPhone14,6-iOS-Version 18.5 (Build 22F76)", "$firebaseAppInstanceId": "4414A67E86F74AF8B91401B04D20999E", "$idfa": "00000000-0000-0000-0000-000000000000", "$idfv": "807089CB-D18F-40A1-8EF8-A38D8186AE4C", "$ip": "99.224.208.246", "$mixpanelDistinctId": "$device:51B72A3B-5502-4A71-BEAA-7C6571E1A5D0"}, "transaction_id": "170002896205359"}, "time": 1753758248}
{"distinct_id": "$device:407725CE-14DA-4632-BE1F-19B83CB0D29B", "event_name": "RC Expiration", "insert_id": "a041947e-62b9-437c-84b4-eca5854407d5", "properties": {"$insert_id": "a041947e-62b9-437c-84b4-eca5854407d5", "$mp_api_endpoint": "api.mixpanel.com", "$mp_api_timestamp_ms": 1753758348004, "aliases": ["$RCAnonymousID:ca3f394211234912af4b95820644b78d", "1K5UD2Xvohe"], "app_id": "app5fe9d54dee", "currency": "USD", "entitlement_id": null, "entitlement_ids": ["CwX3l0tJjXE"], "environment": "PRODUCTION", "expiration_at": "2025-07-29T03:04:55", "expiration_reason": "UNSUBSCRIBE", "mp_processing_time_ms": 1753758358165, "offer_code": null, "original_app_user_id": "$RCAnonymousID:ca3f394211234912af4b95820644b78d", "original_transaction_id": "530002322109299", "period_type": "TRIAL", "presented_offering_id": "gluten.free.eats.3", "product_id": "gluten.free.eats.3.yearly", "purchased_at": "2025-07-22T03:04:55", "revenue": 0, "store": "APP_STORE", "subscriber_attributes": {"$attConsentStatus": "notDetermined", "$branchId": "$device:407725CE-14DA-4632-BE1F-19B83CB0D29B", "$deviceVersion": "iPad14,4-iOS-Version 18.5 (Build 22F76)", "$firebaseAppInstanceId": "B4F81511F6D04EE7BF4CEA6DEE409575", "$idfa": "00000000-0000-0000-0000-000000000000", "$idfv": "3786D11C-B487-4346-A918-6CDC8E5B93E1", "$ip": "76.115.227.173", "$mixpanelDistinctId": "$device:407725CE-14DA-4632-BE1F-19B83CB0D29B"}, "transaction_id": "530002322109299"}, "time": 1753758295}
{"distinct_id": "$device:c7af10f2-9a79-414d-896a-f9d4752c71b2", "event_name": "RC Trial converted", "insert_id": "3b98294e-87f2-42bc-a62d-cbbf60cc1d77", "properties": {"$distinct_id_before_identity": "aXpSqhF9KwW", "$insert_id": "3b98294e-87f2-42bc-a62d-cbbf60cc1d77", "$mp_api_endpoint": "api.mixpanel.com", "$mp_api_timestamp_ms": 1753763340548, "aliases": ["aXpSqhF9KwW"], "app_id": "app3a26e6fb19", "currency": "USD", "entitlement_id": null, "entitlement_ids": ["CwX3l0tJjXE"], "environment": "PRODUCTION", "expiration_at": "2026-07-29T03:50:48", "mp_processing_time_ms": 1753763340645, "offer_code": null, "original_app_user_id": "aXpSqhF9KwW", "original_transaction_id": "GPA.3316-5760-5183-49078", "period_type": "NORMAL", "presented_offering_id": "gluten.free.eats.3", "product_id": "gluten_free_subscription:gluten-free-map-yearly-3", "purchased_at": "2025-07-29T03:50:48", "revenue": 69.99, "store": "PLAY_STORE", "subscriber_attributes": {"$branchId": "aXpSqhF9KwW", "$deviceVersion": "SM-S928U1-android-35", "$firebaseAppInstanceId": "9b9f730f3fc1b9c86b5034e886e88922", "$gpsAdId": "dc00fff9-6502-4fb5-9c06-4d8c1edeafe8", "$ip": "23.25.62.125", "$mixpanelDistinctId": "aXpSqhF9KwW"}, "transaction_id": "GPA.3316-5760-5183-49078..0"}, "time": 1753761048}
